{
  "db_name": "BROADCAST_BASEBALL",
  "tables": {
    "BROADCASTING_CD": {
      "columns": [
        {
          "column_id": 1,
          "name": "BROAD_NM",
          "data_type": "char",
          "max_length": 20,
          "precision": 0,
          "scale": 0,
          "is_nullable": false,
          "is_identity": false,
          "default_value": null,
          "description": null,
          "is_pk": false,
          "is_fk": false,
          "fk_ref_table": null,
          "fk_ref_column": null
        },
        {
          "column_id": 2,
          "name": "BROAD_CD",
          "data_type": "varchar",
          "max_length": 2,
          "precision": 0,
          "scale": 0,
          "is_nullable": false,
          "is_identity": false,
          "default_value": null,
          "description": null,
          "is_pk": true,
          "is_fk": false,
          "fk_ref_table": null,
          "fk_ref_column": null
        }
      ],
      "indexes": [
        {
          "name": "PK_BROADCASTING_CD",
          "type": "CLUSTERED",
          "is_unique": true,
          "is_primary_key": true,
          "columns": "BROAD_CD"
        }
      ],
      "row_count": 12
    },
    "BROADCASTING_RATE": {
      "columns": [
        {
          "column_id": 1,
          "name": "gmkey",
          "data_type": "char",
          "max_length": 13,
          "precision": 0,
          "scale": 0,
          "is_nullable": false,
          "is_identity": false,
          "default_value": null,
          "description": null,
          "is_pk": true,
          "is_fk": false,
          "fk_ref_table": null,
          "fk_ref_column": null
        },
        {
          "column_id": 2,
          "name": "game_flag",
          "data_type": "char",
          "max_length": 1,
          "precision": 0,
          "scale": 0,
          "is_nullable": true,
          "is_identity": false,
          "default_value": null,
          "description": null,
          "is_pk": false,
          "is_fk": false,
          "fk_ref_table": null,
          "fk_ref_column": null
        },
        {
          "column_id": 3,
          "name": "end_flag",
          "data_type": "char",
          "max_length": 1,
          "precision": 0,
          "scale": 0,
          "is_nullable": false,
          "is_identity": false,
          "default_value": null,
          "description": null,
          "is_pk": false,
          "is_fk": false,
          "fk_ref_table": null,
          "fk_ref_column": null
        },
        {
          "column_id": 4,
          "name": "cancel_flag",
          "data_type": "bit",
          "max_length": 1,
          "precision": 1,
          "scale": 0,
          "is_nullable": false,
          "is_identity": false,
          "default_value": "((0))",
          "description": null,
          "is_pk": false,
          "is_fk": false,
          "fk_ref_table": null,
          "fk_ref_column": null
        },
        {
          "column_id": 5,
          "name": "suspended_flag",
          "data_type": "bit",
          "max_length": 1,
          "precision": 1,
          "scale": 0,
          "is_nullable": false,
          "is_identity": false,
          "default_value": "((0))",
          "description": null,
          "is_pk": false,
          "is_fk": false,
          "fk_ref_table": null,
          "fk_ref_column": null
        },
        {
          "column_id": 6,
          "name": "gamedate",
          "data_type": "varchar",
          "max_length": 8,
          "precision": 0,
          "scale": 0,
          "is_nullable": false,
          "is_identity": false,
          "default_value": null,
          "description": null,
          "is_pk": true,
          "is_fk": false,
          "fk_ref_table": null,
          "fk_ref_column": null
        },
        {
          "column_id": 7,
          "name": "gyear",
          "data_type": "char",
          "max_length": 4,
          "precision": 0,
          "scale": 0,
          "is_nullable": false,
          "is_identity": false,
          "default_value": null,
          "description": null,
          "is_pk": false,
          "is_fk": false,
          "fk_ref_table": null,
          "fk_ref_column": null
        },
        {
          "column_id": 8,
          "name": "gmonth",
          "data_type": "char",
          "max_length": 2,
          "precision": 0,
          "scale": 0,
          "is_nullable": false,
          "is_identity": false,
          "default_value": null,
          "description": null,
          "is_pk": false,
          "is_fk": false,
          "fk_ref_table": null,
          "fk_ref_column": null
        },
        {
          "column_id": 9,
          "name": "gday",
          "data_type": "char",
          "max_length": 2,
          "precision": 0,
          "scale": 0,
          "is_nullable": false,
          "is_identity": false,
          "default_value": null,
          "description": null,
          "is_pk": false,
          "is_fk": false,
          "fk_ref_table": null,
          "fk_ref_column": null
        },
        {
          "column_id": 10,
          "name": "gweek",
          "data_type": "varchar",
          "max_length": 2,
          "precision": 0,
          "scale": 0,
          "is_nullable": false,
          "is_identity": false,
          "default_value": null,
          "description": null,
          "is_pk": false,
          "is_fk": false,
          "fk_ref_table": null,
          "fk_ref_column": null
        },
        {
          "column_id": 11,
          "name": "home",
          "data_type": "varchar",
          "max_length": 10,
          "precision": 0,
          "scale": 0,
          "is_nullable": false,
          "is_identity": false,
          "default_value": null,
          "description": null,
          "is_pk": false,
          "is_fk": false,
          "fk_ref_table": null,
          "fk_ref_column": null
        },
        {
          "column_id": 12,
          "name": "home_key",
          "data_type": "char",
          "max_length": 2,
          "precision": 0,
          "scale": 0,
          "is_nullable": false,
          "is_identity": false,
          "default_value": null,
          "description": null,
          "is_pk": false,
          "is_fk": false,
          "fk_ref_table": null,
          "fk_ref_column": null
        },
        {
          "column_id": 13,
          "name": "visit",
          "data_type": "varchar",
          "max_length": 10,
          "precision": 0,
          "scale": 0,
          "is_nullable": false,
          "is_identity": false,
          "default_value": null,
          "description": null,
          "is_pk": false,
          "is_fk": false,
          "fk_ref_table": null,
          "fk_ref_column": null
        },
        {
          "column_id": 14,
          "name": "visit_key",
          "data_type": "char",
          "max_length": 2,
          "precision": 0,
          "scale": 0,
          "is_nullable": false,
          "is_identity": false,
          "default_value": null,
          "description": null,
          "is_pk": false,
          "is_fk": false,
          "fk_ref_table": null,
          "fk_ref_column": null
        },
        {
          "column_id": 15,
          "name": "stadium",
          "data_type": "varchar",
          "max_length": 10,
          "precision": 0,
          "scale": 0,
          "is_nullable": false,
          "is_identity": false,
          "default_value": null,
          "description": null,
          "is_pk": false,
          "is_fk": false,
          "fk_ref_table": null,
          "fk_ref_column": null
        },
        {
          "column_id": 16,
          "name": "stadium_key",
          "data_type": "char",
          "max_length": 2,
          "precision": 0,
          "scale": 0,
          "is_nullable": false,
          "is_identity": false,
          "default_value": null,
          "description": null,
          "is_pk": false,
          "is_fk": false,
          "fk_ref_table": null,
          "fk_ref_column": null
        },
        {
          "column_id": 17,
          "name": "dheader",
          "data_type": "char",
          "max_length": 1,
          "precision": 0,
          "scale": 0,
          "is_nullable": false,
          "is_identity": false,
          "default_value": null,
          "description": null,
          "is_pk": false,
          "is_fk": false,
          "fk_ref_table": null,
          "fk_ref_column": null
        },
        {
          "column_id": 18,
          "name": "gtime",
          "data_type": "char",
          "max_length": 5,
          "precision": 0,
          "scale": 0,
          "is_nullable": false,
          "is_identity": false,
          "default_value": null,
          "description": null,
          "is_pk": false,
          "is_fk": false,
          "fk_ref_table": null,
          "fk_ref_column": null
        },
        {
          "column_id": 19,
          "name": "BROAD_CD",
          "data_type": "varchar",
          "max_length": 2,
          "precision": 0,
          "scale": 0,
          "is_nullable": false,
          "is_identity": false,
          "default_value": null,
          "description": null,
          "is_pk": true,
          "is_fk": false,
          "fk_ref_table": null,
          "fk_ref_column": null
        },
        {
          "column_id": 20,
          "name": "BROAD_RATE",
          "data_type": "float",
          "max_length": 8,
          "precision": 53,
          "scale": 0,
          "is_nullable": false,
          "is_identity": false,
          "default_value": null,
          "description": null,
          "is_pk": false,
          "is_fk": false,
          "fk_ref_table": null,
          "fk_ref_column": null
        },
        {
          "column_id": 21,
          "name": "BROAD_VIEWER",
          "data_type": "float",
          "max_length": 8,
          "precision": 53,
          "scale": 0,
          "is_nullable": false,
          "is_identity": false,
          "default_value": null,
          "description": null,
          "is_pk": true,
          "is_fk": false,
          "fk_ref_table": null,
          "fk_ref_column": null
        },
        {
          "column_id": 22,
          "name": "BROAD_TOTAL_RATE",
          "data_type": "float",
          "max_length": 8,
          "precision": 53,
          "scale": 0,
          "is_nullable": true,
          "is_identity": false,
          "default_value": null,
          "description": null,
          "is_pk": false,
          "is_fk": false,
          "fk_ref_table": null,
          "fk_ref_column": null
        },
        {
          "column_id": 23,
          "name": "BROAD_TOTAL_VIEWER",
          "data_type": "float",
          "max_length": 8,
          "precision": 53,
          "scale": 0,
          "is_nullable": true,
          "is_identity": false,
          "default_value": null,
          "description": null,
          "is_pk": false,
          "is_fk": false,
          "fk_ref_table": null,
          "fk_ref_column": null
        }
      ],
      "indexes": [
        {
          "name": "PK_BROADCASTING_RATE",
          "type": "CLUSTERED",
          "is_unique": true,
          "is_primary_key": true,
          "columns": "gmkey, gamedate, BROAD_CD, BROAD_VIEWER"
        }
      ],
      "row_count": 1589
    },
    "BROADCASTING_RATE_MINOR": {
      "columns": [
        {
          "column_id": 1,
          "name": "gmkey",
          "data_type": "char",
          "max_length": 13,
          "precision": 0,
          "scale": 0,
          "is_nullable": false,
          "is_identity": false,
          "default_value": null,
          "description": null,
          "is_pk": true,
          "is_fk": false,
          "fk_ref_table": null,
          "fk_ref_column": null
        },
        {
          "column_id": 2,
          "name": "game_flag",
          "data_type": "char",
          "max_length": 1,
          "precision": 0,
          "scale": 0,
          "is_nullable": true,
          "is_identity": false,
          "default_value": null,
          "description": null,
          "is_pk": false,
          "is_fk": false,
          "fk_ref_table": null,
          "fk_ref_column": null
        },
        {
          "column_id": 3,
          "name": "cancel_flag",
          "data_type": "bit",
          "max_length": 1,
          "precision": 1,
          "scale": 0,
          "is_nullable": false,
          "is_identity": false,
          "default_value": "((0))",
          "description": null,
          "is_pk": false,
          "is_fk": false,
          "fk_ref_table": null,
          "fk_ref_column": null
        },
        {
          "column_id": 4,
          "name": "suspended_flag",
          "data_type": "bit",
          "max_length": 1,
          "precision": 1,
          "scale": 0,
          "is_nullable": false,
          "is_identity": false,
          "default_value": "((0))",
          "description": null,
          "is_pk": false,
          "is_fk": false,
          "fk_ref_table": null,
          "fk_ref_column": null
        },
        {
          "column_id": 5,
          "name": "gamedate",
          "data_type": "varchar",
          "max_length": 8,
          "precision": 0,
          "scale": 0,
          "is_nullable": false,
          "is_identity": false,
          "default_value": null,
          "description": null,
          "is_pk": true,
          "is_fk": false,
          "fk_ref_table": null,
          "fk_ref_column": null
        },
        {
          "column_id": 6,
          "name": "gyear",
          "data_type": "char",
          "max_length": 4,
          "precision": 0,
          "scale": 0,
          "is_nullable": false,
          "is_identity": false,
          "default_value": null,
          "description": null,
          "is_pk": false,
          "is_fk": false,
          "fk_ref_table": null,
          "fk_ref_column": null
        },
        {
          "column_id": 7,
          "name": "gmonth",
          "data_type": "char",
          "max_length": 2,
          "precision": 0,
          "scale": 0,
          "is_nullable": false,
          "is_identity": false,
          "default_value": null,
          "description": null,
          "is_pk": false,
          "is_fk": false,
          "fk_ref_table": null,
          "fk_ref_column": null
        },
        {
          "column_id": 8,
          "name": "gday",
          "data_type": "char",
          "max_length": 2,
          "precision": 0,
          "scale": 0,
          "is_nullable": false,
          "is_identity": false,
          "default_value": null,
          "description": null,
          "is_pk": false,
          "is_fk": false,
          "fk_ref_table": null,
          "fk_ref_column": null
        },
        {
          "column_id": 9,
          "name": "gweek",
          "data_type": "varchar",
          "max_length": 2,
          "precision": 0,
          "scale": 0,
          "is_nullable": false,
          "is_identity": false,
          "default_value": null,
          "description": null,
          "is_pk": false,
          "is_fk": false,
          "fk_ref_table": null,
          "fk_ref_column": null
        },
        {
          "column_id": 10,
          "name": "home",
          "data_type": "varchar",
          "max_length": 10,
          "precision": 0,
          "scale": 0,
          "is_nullable": false,
          "is_identity": false,
          "default_value": null,
          "description": null,
          "is_pk": false,
          "is_fk": false,
          "fk_ref_table": null,
          "fk_ref_column": null
        },
        {
          "column_id": 11,
          "name": "home_key",
          "data_type": "char",
          "max_length": 2,
          "precision": 0,
          "scale": 0,
          "is_nullable": false,
          "is_identity": false,
          "default_value": null,
          "description": null,
          "is_pk": false,
          "is_fk": false,
          "fk_ref_table": null,
          "fk_ref_column": null
        },
        {
          "column_id": 12,
          "name": "visit",
          "data_type": "varchar",
          "max_length": 10,
          "precision": 0,
          "scale": 0,
          "is_nullable": false,
          "is_identity": false,
          "default_value": null,
          "description": null,
          "is_pk": false,
          "is_fk": false,
          "fk_ref_table": null,
          "fk_ref_column": null
        },
        {
          "column_id": 13,
          "name": "visit_key",
          "data_type": "char",
          "max_length": 2,
          "precision": 0,
          "scale": 0,
          "is_nullable": false,
          "is_identity": false,
          "default_value": null,
          "description": null,
          "is_pk": false,
          "is_fk": false,
          "fk_ref_table": null,
          "fk_ref_column": null
        },
        {
          "column_id": 14,
          "name": "stadium",
          "data_type": "varchar",
          "max_length": 10,
          "precision": 0,
          "scale": 0,
          "is_nullable": false,
          "is_identity": false,
          "default_value": null,
          "description": null,
          "is_pk": false,
          "is_fk": false,
          "fk_ref_table": null,
          "fk_ref_column": null
        },
        {
          "column_id": 15,
          "name": "dheader",
          "data_type": "char",
          "max_length": 1,
          "precision": 0,
          "scale": 0,
          "is_nullable": false,
          "is_identity": false,
          "default_value": null,
          "description": null,
          "is_pk": false,
          "is_fk": false,
          "fk_ref_table": null,
          "fk_ref_column": null
        },
        {
          "column_id": 16,
          "name": "gtime",
          "data_type": "char",
          "max_length": 5,
          "precision": 0,
          "scale": 0,
          "is_nullable": false,
          "is_identity": false,
          "default_value": null,
          "description": null,
          "is_pk": false,
          "is_fk": false,
          "fk_ref_table": null,
          "fk_ref_column": null
        },
        {
          "column_id": 17,
          "name": "BROAD_CD",
          "data_type": "varchar",
          "max_length": 2,
          "precision": 0,
          "scale": 0,
          "is_nullable": false,
          "is_identity": false,
          "default_value": null,
          "description": null,
          "is_pk": true,
          "is_fk": false,
          "fk_ref_table": null,
          "fk_ref_column": null
        },
        {
          "column_id": 18,
          "name": "BROAD_RATE",
          "data_type": "float",
          "max_length": 8,
          "precision": 53,
          "scale": 0,
          "is_nullable": false,
          "is_identity": false,
          "default_value": null,
          "description": null,
          "is_pk": false,
          "is_fk": false,
          "fk_ref_table": null,
          "fk_ref_column": null
        },
        {
          "column_id": 19,
          "name": "BROAD_VIEWER",
          "data_type": "float",
          "max_length": 8,
          "precision": 53,
          "scale": 0,
          "is_nullable": false,
          "is_identity": false,
          "default_value": null,
          "description": null,
          "is_pk": true,
          "is_fk": false,
          "fk_ref_table": null,
          "fk_ref_column": null
        },
        {
          "column_id": 20,
          "name": "BROAD_TOTAL_RATE",
          "data_type": "float",
          "max_length": 8,
          "precision": 53,
          "scale": 0,
          "is_nullable": true,
          "is_identity": false,
          "default_value": null,
          "description": null,
          "is_pk": false,
          "is_fk": false,
          "fk_ref_table": null,
          "fk_ref_column": null
        },
        {
          "column_id": 21,
          "name": "BROAD_TOTAL_VIEWER",
          "data_type": "float",
          "max_length": 8,
          "precision": 53,
          "scale": 0,
          "is_nullable": true,
          "is_identity": false,
          "default_value": null,
          "description": null,
          "is_pk": false,
          "is_fk": false,
          "fk_ref_table": null,
          "fk_ref_column": null
        }
      ],
      "indexes": [
        {
          "name": "PK_BROADCASTING_RATE_MINOR",
          "type": "CLUSTERED",
          "is_unique": true,
          "is_primary_key": true,
          "columns": "gmkey, gamedate, BROAD_CD, BROAD_VIEWER"
        }
      ],
      "row_count": 93
    },
    "BROADCASTING_schedule": {
      "columns": [
        {
          "column_id": 1,
          "name": "gmkey",
          "data_type": "char",
          "max_length": 13,
          "precision": 0,
          "scale": 0,
          "is_nullable": false,
          "is_identity": false,
          "default_value": null,
          "description": null,
          "is_pk": false,
          "is_fk": false,
          "fk_ref_table": null,
          "fk_ref_column": null
        },
        {
          "column_id": 2,
          "name": "game_flag",
          "data_type": "char",
          "max_length": 1,
          "precision": 0,
          "scale": 0,
          "is_nullable": true,
          "is_identity": false,
          "default_value": null,
          "description": null,
          "is_pk": false,
          "is_fk": false,
          "fk_ref_table": null,
          "fk_ref_column": null
        },
        {
          "column_id": 3,
          "name": "end_flag",
          "data_type": "char",
          "max_length": 1,
          "precision": 0,
          "scale": 0,
          "is_nullable": false,
          "is_identity": false,
          "default_value": null,
          "description": null,
          "is_pk": false,
          "is_fk": false,
          "fk_ref_table": null,
          "fk_ref_column": null
        },
        {
          "column_id": 4,
          "name": "cancel_flag",
          "data_type": "bit",
          "max_length": 1,
          "precision": 1,
          "scale": 0,
          "is_nullable": false,
          "is_identity": false,
          "default_value": "((0))",
          "description": null,
          "is_pk": false,
          "is_fk": false,
          "fk_ref_table": null,
          "fk_ref_column": null
        },
        {
          "column_id": 5,
          "name": "suspended_flag",
          "data_type": "bit",
          "max_length": 1,
          "precision": 1,
          "scale": 0,
          "is_nullable": false,
          "is_identity": false,
          "default_value": "((0))",
          "description": null,
          "is_pk": false,
          "is_fk": false,
          "fk_ref_table": null,
          "fk_ref_column": null
        },
        {
          "column_id": 6,
          "name": "gamedate",
          "data_type": "varchar",
          "max_length": 8,
          "precision": 0,
          "scale": 0,
          "is_nullable": false,
          "is_identity": false,
          "default_value": null,
          "description": null,
          "is_pk": false,
          "is_fk": false,
          "fk_ref_table": null,
          "fk_ref_column": null
        },
        {
          "column_id": 7,
          "name": "gyear",
          "data_type": "char",
          "max_length": 4,
          "precision": 0,
          "scale": 0,
          "is_nullable": false,
          "is_identity": false,
          "default_value": null,
          "description": null,
          "is_pk": false,
          "is_fk": false,
          "fk_ref_table": null,
          "fk_ref_column": null
        },
        {
          "column_id": 8,
          "name": "gmonth",
          "data_type": "char",
          "max_length": 2,
          "precision": 0,
          "scale": 0,
          "is_nullable": false,
          "is_identity": false,
          "default_value": null,
          "description": null,
          "is_pk": false,
          "is_fk": false,
          "fk_ref_table": null,
          "fk_ref_column": null
        },
        {
          "column_id": 9,
          "name": "gday",
          "data_type": "char",
          "max_length": 2,
          "precision": 0,
          "scale": 0,
          "is_nullable": false,
          "is_identity": false,
          "default_value": null,
          "description": null,
          "is_pk": false,
          "is_fk": false,
          "fk_ref_table": null,
          "fk_ref_column": null
        },
        {
          "column_id": 10,
          "name": "gweek",
          "data_type": "varchar",
          "max_length": 2,
          "precision": 0,
          "scale": 0,
          "is_nullable": false,
          "is_identity": false,
          "default_value": null,
          "description": null,
          "is_pk": false,
          "is_fk": false,
          "fk_ref_table": null,
          "fk_ref_column": null
        },
        {
          "column_id": 11,
          "name": "home",
          "data_type": "varchar",
          "max_length": 10,
          "precision": 0,
          "scale": 0,
          "is_nullable": false,
          "is_identity": false,
          "default_value": null,
          "description": null,
          "is_pk": false,
          "is_fk": false,
          "fk_ref_table": null,
          "fk_ref_column": null
        },
        {
          "column_id": 12,
          "name": "home_key",
          "data_type": "char",
          "max_length": 2,
          "precision": 0,
          "scale": 0,
          "is_nullable": false,
          "is_identity": false,
          "default_value": null,
          "description": null,
          "is_pk": false,
          "is_fk": false,
          "fk_ref_table": null,
          "fk_ref_column": null
        },
        {
          "column_id": 13,
          "name": "visit",
          "data_type": "varchar",
          "max_length": 10,
          "precision": 0,
          "scale": 0,
          "is_nullable": false,
          "is_identity": false,
          "default_value": null,
          "description": null,
          "is_pk": false,
          "is_fk": false,
          "fk_ref_table": null,
          "fk_ref_column": null
        },
        {
          "column_id": 14,
          "name": "visit_key",
          "data_type": "char",
          "max_length": 2,
          "precision": 0,
          "scale": 0,
          "is_nullable": false,
          "is_identity": false,
          "default_value": null,
          "description": null,
          "is_pk": false,
          "is_fk": false,
          "fk_ref_table": null,
          "fk_ref_column": null
        },
        {
          "column_id": 15,
          "name": "stadium",
          "data_type": "varchar",
          "max_length": 10,
          "precision": 0,
          "scale": 0,
          "is_nullable": false,
          "is_identity": false,
          "default_value": null,
          "description": null,
          "is_pk": false,
          "is_fk": false,
          "fk_ref_table": null,
          "fk_ref_column": null
        },
        {
          "column_id": 16,
          "name": "stadium_key",
          "data_type": "char",
          "max_length": 2,
          "precision": 0,
          "scale": 0,
          "is_nullable": false,
          "is_identity": false,
          "default_value": null,
          "description": null,
          "is_pk": false,
          "is_fk": false,
          "fk_ref_table": null,
          "fk_ref_column": null
        },
        {
          "column_id": 17,
          "name": "dheader",
          "data_type": "char",
          "max_length": 1,
          "precision": 0,
          "scale": 0,
          "is_nullable": false,
          "is_identity": false,
          "default_value": null,
          "description": null,
          "is_pk": false,
          "is_fk": false,
          "fk_ref_table": null,
          "fk_ref_column": null
        },
        {
          "column_id": 18,
          "name": "gtime",
          "data_type": "char",
          "max_length": 5,
          "precision": 0,
          "scale": 0,
          "is_nullable": false,
          "is_identity": false,
          "default_value": null,
          "description": null,
          "is_pk": false,
          "is_fk": false,
          "fk_ref_table": null,
          "fk_ref_column": null
        },
        {
          "column_id": 19,
          "name": "TSM",
          "data_type": "char",
          "max_length": 1,
          "precision": 0,
          "scale": 0,
          "is_nullable": false,
          "is_identity": false,
          "default_value": "((0))",
          "description": null,
          "is_pk": false,
          "is_fk": false,
          "fk_ref_table": null,
          "fk_ref_column": null
        },
        {
          "column_id": 20,
          "name": "REFFER_CAM_TVING",
          "data_type": "char",
          "max_length": 1,
          "precision": 0,
          "scale": 0,
          "is_nullable": false,
          "is_identity": false,
          "default_value": "((0))",
          "description": null,
          "is_pk": false,
          "is_fk": false,
          "fk_ref_table": null,
          "fk_ref_column": null
        },
        {
          "column_id": 21,
          "name": "REFFER_CAM_MBC",
          "data_type": "char",
          "max_length": 1,
          "precision": 0,
          "scale": 0,
          "is_nullable": false,
          "is_identity": false,
          "default_value": "((0))",
          "description": null,
          "is_pk": false,
          "is_fk": false,
          "fk_ref_table": null,
          "fk_ref_column": null
        },
        {
          "column_id": 22,
          "name": "CGV",
          "data_type": "char",
          "max_length": 1,
          "precision": 0,
          "scale": 0,
          "is_nullable": false,
          "is_identity": false,
          "default_value": "((0))",
          "description": null,
          "is_pk": false,
          "is_fk": false,
          "fk_ref_table": null,
          "fk_ref_column": null
        }
      ],
      "indexes": [],
      "row_count": 823
    },
    "BROADCASTING_schedule_minor ": {
      "columns": [
        {
          "column_id": 1,
          "name": "gmkey",
          "data_type": "char",
          "max_length": 13,
          "precision": 0,
          "scale": 0,
          "is_nullable": false,
          "is_identity": false,
          "default_value": null,
          "description": null,
          "is_pk": false,
          "is_fk": false,
          "fk_ref_table": null,
          "fk_ref_column": null
        },
        {
          "column_id": 2,
          "name": "game_flag",
          "data_type": "char",
          "max_length": 1,
          "precision": 0,
          "scale": 0,
          "is_nullable": true,
          "is_identity": false,
          "default_value": null,
          "description": null,
          "is_pk": false,
          "is_fk": false,
          "fk_ref_table": null,
          "fk_ref_column": null
        },
        {
          "column_id": 3,
          "name": "end_flag",
          "data_type": "char",
          "max_length": 1,
          "precision": 0,
          "scale": 0,
          "is_nullable": false,
          "is_identity": false,
          "default_value": null,
          "description": null,
          "is_pk": false,
          "is_fk": false,
          "fk_ref_table": null,
          "fk_ref_column": null
        },
        {
          "column_id": 4,
          "name": "cancel_flag",
          "data_type": "bit",
          "max_length": 1,
          "precision": 1,
          "scale": 0,
          "is_nullable": false,
          "is_identity": false,
          "default_value": "((0))",
          "description": null,
          "is_pk": false,
          "is_fk": false,
          "fk_ref_table": null,
          "fk_ref_column": null
        },
        {
          "column_id": 5,
          "name": "suspended_flag",
          "data_type": "bit",
          "max_length": 1,
          "precision": 1,
          "scale": 0,
          "is_nullable": false,
          "is_identity": false,
          "default_value": "((0))",
          "description": null,
          "is_pk": false,
          "is_fk": false,
          "fk_ref_table": null,
          "fk_ref_column": null
        },
        {
          "column_id": 6,
          "name": "gamedate",
          "data_type": "varchar",
          "max_length": 8,
          "precision": 0,
          "scale": 0,
          "is_nullable": false,
          "is_identity": false,
          "default_value": null,
          "description": null,
          "is_pk": false,
          "is_fk": false,
          "fk_ref_table": null,
          "fk_ref_column": null
        },
        {
          "column_id": 7,
          "name": "gyear",
          "data_type": "char",
          "max_length": 4,
          "precision": 0,
          "scale": 0,
          "is_nullable": false,
          "is_identity": false,
          "default_value": null,
          "description": null,
          "is_pk": false,
          "is_fk": false,
          "fk_ref_table": null,
          "fk_ref_column": null
        },
        {
          "column_id": 8,
          "name": "gmonth",
          "data_type": "char",
          "max_length": 2,
          "precision": 0,
          "scale": 0,
          "is_nullable": false,
          "is_identity": false,
          "default_value": null,
          "description": null,
          "is_pk": false,
          "is_fk": false,
          "fk_ref_table": null,
          "fk_ref_column": null
        },
        {
          "column_id": 9,
          "name": "gday",
          "data_type": "char",
          "max_length": 2,
          "precision": 0,
          "scale": 0,
          "is_nullable": false,
          "is_identity": false,
          "default_value": null,
          "description": null,
          "is_pk": false,
          "is_fk": false,
          "fk_ref_table": null,
          "fk_ref_column": null
        },
        {
          "column_id": 10,
          "name": "gweek",
          "data_type": "varchar",
          "max_length": 2,
          "precision": 0,
          "scale": 0,
          "is_nullable": false,
          "is_identity": false,
          "default_value": null,
          "description": null,
          "is_pk": false,
          "is_fk": false,
          "fk_ref_table": null,
          "fk_ref_column": null
        },
        {
          "column_id": 11,
          "name": "home",
          "data_type": "varchar",
          "max_length": 10,
          "precision": 0,
          "scale": 0,
          "is_nullable": false,
          "is_identity": false,
          "default_value": null,
          "description": null,
          "is_pk": false,
          "is_fk": false,
          "fk_ref_table": null,
          "fk_ref_column": null
        },
        {
          "column_id": 12,
          "name": "home_key",
          "data_type": "char",
          "max_length": 2,
          "precision": 0,
          "scale": 0,
          "is_nullable": false,
          "is_identity": false,
          "default_value": null,
          "description": null,
          "is_pk": false,
          "is_fk": false,
          "fk_ref_table": null,
          "fk_ref_column": null
        },
        {
          "column_id": 13,
          "name": "visit",
          "data_type": "varchar",
          "max_length": 10,
          "precision": 0,
          "scale": 0,
          "is_nullable": false,
          "is_identity": false,
          "default_value": null,
          "description": null,
          "is_pk": false,
          "is_fk": false,
          "fk_ref_table": null,
          "fk_ref_column": null
        },
        {
          "column_id": 14,
          "name": "visit_key",
          "data_type": "char",
          "max_length": 2,
          "precision": 0,
          "scale": 0,
          "is_nullable": false,
          "is_identity": false,
          "default_value": null,
          "description": null,
          "is_pk": false,
          "is_fk": false,
          "fk_ref_table": null,
          "fk_ref_column": null
        },
        {
          "column_id": 15,
          "name": "stadium",
          "data_type": "varchar",
          "max_length": 10,
          "precision": 0,
          "scale": 0,
          "is_nullable": false,
          "is_identity": false,
          "default_value": null,
          "description": null,
          "is_pk": false,
          "is_fk": false,
          "fk_ref_table": null,
          "fk_ref_column": null
        },
        {
          "column_id": 16,
          "name": "stadium_key",
          "data_type": "char",
          "max_length": 2,
          "precision": 0,
          "scale": 0,
          "is_nullable": false,
          "is_identity": false,
          "default_value": null,
          "description": null,
          "is_pk": false,
          "is_fk": false,
          "fk_ref_table": null,
          "fk_ref_column": null
        },
        {
          "column_id": 17,
          "name": "dheader",
          "data_type": "char",
          "max_length": 1,
          "precision": 0,
          "scale": 0,
          "is_nullable": false,
          "is_identity": false,
          "default_value": null,
          "description": null,
          "is_pk": false,
          "is_fk": false,
          "fk_ref_table": null,
          "fk_ref_column": null
        },
        {
          "column_id": 18,
          "name": "gtime",
          "data_type": "char",
          "max_length": 5,
          "precision": 0,
          "scale": 0,
          "is_nullable": false,
          "is_identity": false,
          "default_value": null,
          "description": null,
          "is_pk": false,
          "is_fk": false,
          "fk_ref_table": null,
          "fk_ref_column": null
        },
        {
          "column_id": 19,
          "name": "REFFER_CAM",
          "data_type": "char",
          "max_length": 1,
          "precision": 0,
          "scale": 0,
          "is_nullable": false,
          "is_identity": false,
          "default_value": "((0))",
          "description": null,
          "is_pk": false,
          "is_fk": false,
          "fk_ref_table": null,
          "fk_ref_column": null
        },
        {
          "column_id": 20,
          "name": "TVN",
          "data_type": "char",
          "max_length": 1,
          "precision": 0,
          "scale": 0,
          "is_nullable": false,
          "is_identity": false,
          "default_value": "((0))",
          "description": null,
          "is_pk": false,
          "is_fk": false,
          "fk_ref_table": null,
          "fk_ref_column": null
        }
      ],
      "indexes": [],
      "row_count": 678
    }
  }
}